nodestream_plugin_pedantic/__init__.py
nodestream_plugin_pedantic/audits.py
nodestream_plugin_pedantic-0.14.0.dist-info/LICENSE
nodestream_plugin_pedantic-0.14.0.dist-info/METADATA
nodestream_plugin_pedantic-0.14.0.dist-info/WHEEL
nodestream_plugin_pedantic-0.14.0.dist-info/entry_points.txt
nodestream_plugin_pedantic-0.14.0.dist-info/RECORD
