Metadata-Version: 2.3
Name: nodestream-plugin-pedantic
Version: 0.14.0
Summary: A nodestream plugin that provides a series of audits to ensure high quality and consistent nodestream projects.
License: Apache-2.0
Keywords: etl,neo4j,declarative,data,kafka,ingest,nodestream
Author: Zach Probst
Author-email: Zach_Probst@intuit.com
Requires-Python: >=3.10,<4.0
Classifier: Development Status :: 4 - Beta
Classifier: Environment :: Console
Classifier: Intended Audience :: Developers
Classifier: Intended Audience :: Information Technology
Classifier: License :: OSI Approved :: Apache Software License
Classifier: Natural Language :: English
Classifier: Programming Language :: Python :: 3
Classifier: Programming Language :: Python :: 3.10
Classifier: Programming Language :: Python :: 3.11
Classifier: Programming Language :: Python :: 3.12
Classifier: Programming Language :: Python :: 3.13
Classifier: Topic :: Database
Requires-Dist: inflection (>=0.5.1,<0.6.0)
Requires-Dist: nodestream (>=0.14.0,<0.15.0)
Project-URL: Documentation, https://nodestream-proj.github.io/nodestream-plugin-pedantic
Project-URL: Homepage, https://github.com/nodestream-proj/nodestream
Project-URL: Repository, https://github.com/nodestream-proj/nodestream-plugin-pedantic
